setup.py
xprize_data/__init__.py
xprize_data.egg-info/PKG-INFO
xprize_data.egg-info/SOURCES.txt
xprize_data.egg-info/dependency_links.txt
xprize_data.egg-info/not-zip-safe
xprize_data.egg-info/requires.txt
xprize_data.egg-info/top_level.txt