Metadata-Version: 1.0
Name: xprize-data
Version: 0.4
Summary: Xprize Data Commons
Home-page: https://github.com/xprizewebadmin/Data-Commons
Author: Max Cappellari
Author-email: max@xprize.org
License: MIT
Platform: UNKNOWN
